{
  "id": "",
  "name": "",
  "font_family": "iconfont",
  "css_prefix_text": "icon-",
  "description": "",
  "glyphs": [
    {
      "icon_id": "117006",
      "name": "商品",
      "font_class": "shangpin",
      "unicode": "e624",
      "unicode_decimal": 58916
    },
    {
      "icon_id": "592261",
      "name": "信息",
      "font_class": "xinxi",
      "unicode": "e615",
      "unicode_decimal": 58901
    },
    {
      "icon_id": "600345",
      "name": "房子",
      "font_class": "2",
      "unicode": "e602",
      "unicode_decimal": 58882
    },
    {
      "icon_id": "648776",
      "name": "婴儿车",
      "font_class": "yingerche",
      "unicode": "e61f",
      "unicode_decimal": 58911
    },
    {
      "icon_id": "777305",
      "name": "人群",
      "font_class": "renqun-copy",
      "unicode": "e600",
      "unicode_decimal": 58880
    },
    {
      "icon_id": "880429",
      "name": "扳手",
      "font_class": "editor2",
      "unicode": "e62e",
      "unicode_decimal": 58926
    },
    {
      "icon_id": "1005151",
      "name": "日常销售",
      "font_class": "richangxiaoshou",
      "unicode": "e6ef",
      "unicode_decimal": 59119
    },
    {
      "icon_id": "1192381",
      "name": "话题 (1)",
      "font_class": "huati1",
      "unicode": "e623",
      "unicode_decimal": 58915
    },
    {
      "icon_id": "1494331",
      "name": "生日",
      "font_class": "shengri1",
      "unicode": "e603",
      "unicode_decimal": 58883
    },
    {
      "icon_id": "1533439",
      "name": "餐具",
      "font_class": "canju",
      "unicode": "e6de",
      "unicode_decimal": 59102
    },
    {
      "icon_id": "1717472",
      "name": "城市",
      "font_class": "map",
      "unicode": "e626",
      "unicode_decimal": 58918
    },
    {
      "icon_id": "1899211",
      "name": "放大镜",
      "font_class": "fangdajing",
      "unicode": "e612",
      "unicode_decimal": 58898
    },
    {
      "icon_id": "2029104",
      "name": "蜂巢",
      "font_class": "fengchao",
      "unicode": "e649",
      "unicode_decimal": 58953
    },
    {
      "icon_id": "2032256",
      "name": "钻石",
      "font_class": "zuanshi-copy",
      "unicode": "e504",
      "unicode_decimal": 58628
    },
    {
      "icon_id": "2240524",
      "name": "性别",
      "font_class": "xingbie",
      "unicode": "e609",
      "unicode_decimal": 58889
    },
    {
      "icon_id": "2258168",
      "name": "其他",
      "font_class": "qita",
      "unicode": "e61e",
      "unicode_decimal": 58910
    },
    {
      "icon_id": "2534141",
      "name": "房子 hover",
      "font_class": "fangzihover",
      "unicode": "e668",
      "unicode_decimal": 58984
    },
    {
      "icon_id": "2816203",
      "name": "左箭头",
      "font_class": "arrow-right",
      "unicode": "e517",
      "unicode_decimal": 58647
    },
    {
      "icon_id": "2979768",
      "name": "射箭",
      "font_class": "shejian",
      "unicode": "e613",
      "unicode_decimal": 58899
    },
    {
      "icon_id": "3093825",
      "name": "右箭头",
      "font_class": "arrow-right1",
      "unicode": "e501",
      "unicode_decimal": 58625
    },
    {
      "icon_id": "3102825",
      "name": "下箭头",
      "font_class": "icon",
      "unicode": "e509",
      "unicode_decimal": 58633
    },
    {
      "icon_id": "3216129",
      "name": "烹饪",
      "font_class": "icon--",
      "unicode": "e738",
      "unicode_decimal": 59192
    },
    {
      "icon_id": "3265632",
      "name": "默认",
      "font_class": "moren",
      "unicode": "e627",
      "unicode_decimal": 58919
    },
    {
      "icon_id": "3297771",
      "name": "钻石",
      "font_class": "zuanshi",
      "unicode": "e61a",
      "unicode_decimal": 58906
    },
    {
      "icon_id": "3398861",
      "name": "灯泡",
      "font_class": "dengpao",
      "unicode": "e604",
      "unicode_decimal": 58884
    },
    {
      "icon_id": "3610808",
      "name": "加入",
      "font_class": "jiaru",
      "unicode": "e6b8",
      "unicode_decimal": 59064
    },
    {
      "icon_id": "3621821",
      "name": "发送失败",
      "font_class": "fasongshibai",
      "unicode": "e706",
      "unicode_decimal": 59142
    },
    {
      "icon_id": "3696365",
      "name": "基本信息",
      "font_class": "jibenxinxi",
      "unicode": "e65e",
      "unicode_decimal": 58974
    },
    {
      "icon_id": "4118489",
      "name": "语音",
      "font_class": "yuyin",
      "unicode": "e70b",
      "unicode_decimal": 59147
    },
    {
      "icon_id": "4275426",
      "name": "发送",
      "font_class": "fasong",
      "unicode": "e66f",
      "unicode_decimal": 58991
    },
    {
      "icon_id": "4457620",
      "name": "环保 叶子 树叶 线性",
      "font_class": "huanbaoyezishuyexianxing",
      "unicode": "ea1a",
      "unicode_decimal": 59930
    },
    {
      "icon_id": "4998065",
      "name": "kg",
      "font_class": "kg",
      "unicode": "e731",
      "unicode_decimal": 59185
    },
    {
      "icon_id": "5170011",
      "name": "收 藏",
      "font_class": "shoucang",
      "unicode": "e6a3",
      "unicode_decimal": 59043
    },
    {
      "icon_id": "5199731",
      "name": "心率",
      "font_class": "xinshuai",
      "unicode": "e690",
      "unicode_decimal": 59024
    },
    {
      "icon_id": "5213279",
      "name": "键盘",
      "font_class": "jianpan",
      "unicode": "e638",
      "unicode_decimal": 58936
    },
    {
      "icon_id": "5267407",
      "name": "记录",
      "font_class": "jilu",
      "unicode": "e653",
      "unicode_decimal": 58963
    },
    {
      "icon_id": "5461956",
      "name": "两个人",
      "font_class": "lianggeren",
      "unicode": "e53d",
      "unicode_decimal": 58685
    },
    {
      "icon_id": "5641699",
      "name": "客服",
      "font_class": "kefu",
      "unicode": "e622",
      "unicode_decimal": 58914
    },
    {
      "icon_id": "5902507",
      "name": "医疗健康-我的体质健康-学生",
      "font_class": "yiliaojiankang-wodetizhijiankang-xuesheng",
      "unicode": "e808",
      "unicode_decimal": 59400
    },
    {
      "icon_id": "5920130",
      "name": "订单",
      "font_class": "icon--copy",
      "unicode": "e502",
      "unicode_decimal": 58626
    },
    {
      "icon_id": "6606688",
      "name": "人",
      "font_class": "ren",
      "unicode": "e65b",
      "unicode_decimal": 58971
    },
    {
      "icon_id": "7139741",
      "name": "药瓶",
      "font_class": "yao",
      "unicode": "e605",
      "unicode_decimal": 58885
    },
    {
      "icon_id": "7354829",
      "name": "树叶",
      "font_class": "shuye",
      "unicode": "e619",
      "unicode_decimal": 58905
    },
    {
      "icon_id": "7447773",
      "name": "我 的",
      "font_class": "wode",
      "unicode": "e64c",
      "unicode_decimal": 58956
    },
    {
      "icon_id": "9187092",
      "name": "加号",
      "font_class": "hao",
      "unicode": "e533",
      "unicode_decimal": 58675
    },
    {
      "icon_id": "9238874",
      "name": "-vc",
      "font_class": "-vc",
      "unicode": "edba",
      "unicode_decimal": 60858
    },
    {
      "icon_id": "9363570",
      "name": "气球",
      "font_class": "qiqiu",
      "unicode": "e629",
      "unicode_decimal": 58921
    },
    {
      "icon_id": "9419360",
      "name": "购物车",
      "font_class": "gouwuche",
      "unicode": "e506",
      "unicode_decimal": 58630
    },
    {
      "icon_id": "9714403",
      "name": "定位",
      "font_class": "location-copy",
      "unicode": "e503",
      "unicode_decimal": 58627
    },
    {
      "icon_id": "10399775",
      "name": "体检",
      "font_class": "tijian",
      "unicode": "e87c",
      "unicode_decimal": 59516
    },
    {
      "icon_id": "11363530",
      "name": "药瓶 12",
      "font_class": "yaoping",
      "unicode": "e663",
      "unicode_decimal": 58979
    },
    {
      "icon_id": "11588280",
      "name": "分 享",
      "font_class": "fenxiang",
      "unicode": "e62f",
      "unicode_decimal": 58927
    },
    {
      "icon_id": "12902177",
      "name": "通讯录",
      "font_class": "tongxunlu",
      "unicode": "e673",
      "unicode_decimal": 58995
    },
    {
      "icon_id": "12905312",
      "name": "加号",
      "font_class": "addTodo-nav",
      "unicode": "e505",
      "unicode_decimal": 58629
    },
    {
      "icon_id": "12909667",
      "name": "帮 助",
      "font_class": "bangzhu",
      "unicode": "e606",
      "unicode_decimal": 58886
    },
    {
      "icon_id": "13017034",
      "name": "完成",
      "font_class": "wancheng",
      "unicode": "e607",
      "unicode_decimal": 58887
    },
    {
      "icon_id": "13039084",
      "name": "时间",
      "font_class": "shijian",
      "unicode": "e66d",
      "unicode_decimal": 58989
    },
    {
      "icon_id": "13043186",
      "name": "账号",
      "font_class": "zhanghao",
      "unicode": "e610",
      "unicode_decimal": 58896
    },
    {
      "icon_id": "13044805",
      "name": "我 的",
      "font_class": "wodedangxuan",
      "unicode": "e507",
      "unicode_decimal": 58631
    }
  ]
}
